pyloot/__init__.py
pyloot/__main__.py
pyloot/cli.py
pyloot/collector.py
pyloot/server.py
pyloot/types.py
pyloot/utils.py
pyloot/backends/__init__.py
pyloot/backends/base.py
pyloot/backends/http.py
pyloot/backends/memory.py
pyloot/static/bundle.css
pyloot/static/bundle.js
pyloot/static/index.html
pyloot-0.1.0.dist-info/LICENSE
pyloot-0.1.0.dist-info/METADATA
pyloot-0.1.0.dist-info/WHEEL
pyloot-0.1.0.dist-info/entry_points.txt
pyloot-0.1.0.dist-info/top_level.txt
pyloot-0.1.0.dist-info/RECORD
