Metadata-Version: 2.1
Name: pyloot
Version: 0.1.0
Summary: Multiprocessing compatible memory leak debugger inspired by dozer/dowser
Home-page: https://github.com/reallistic/pyloot
Author: Michael Chase
License: MIT
Keywords: memory profiler multiprocessing wsgi asgi
Platform: UNKNOWN
Classifier: Development Status :: 3 - Alpha
Classifier: Intended Audience :: Developers
Classifier: License :: Public Domain
Classifier: Programming Language :: Python :: 3.7
Classifier: Programming Language :: Python :: 3.8
Classifier: Programming Language :: Python :: 3.9
Classifier: Programming Language :: Python :: 3.10
Classifier: Programming Language :: Python :: 3.11
Classifier: Topic :: Internet :: WWW/HTTP
Classifier: Topic :: Internet :: WWW/HTTP :: WSGI
Classifier: Topic :: Software Development :: Libraries :: Python Modules
Requires-Python: >=3.7
License-File: LICENSE
Requires-Dist: WebOb (>=1.2)
Requires-Dist: importlib-resources
Provides-Extra: test
Requires-Dist: pytest ; extra == 'test'
